id10terr/__init__.py
id10terr/__version__.py
id10terr/errors.py
id10terr/interface.py
id10terr/warnings.py
id10terr-1.0.0.dist-info/licenses/LICENSE
id10terr-1.0.0.dist-info/METADATA
id10terr-1.0.0.dist-info/WHEEL
id10terr-1.0.0.dist-info/top_level.txt
id10terr-1.0.0.dist-info/zip-safe
id10terr-1.0.0.dist-info/RECORD
